etherdump/__init__.py
etherdump/etherpad.py
etherdump/magicwords.py
etherdump/commands/__init__.py
etherdump/commands/appendmeta.py
etherdump/commands/common.py
etherdump/commands/creatediffhtml.py
etherdump/commands/deletepad.py
etherdump/commands/dumpcsv.py
etherdump/commands/gethtml.py
etherdump/commands/gettext.py
etherdump/commands/html5tidy.py
etherdump/commands/index.py
etherdump/commands/init.py
etherdump/commands/join.py
etherdump/commands/list.py
etherdump/commands/listauthors.py
etherdump/commands/oauthtest.py
etherdump/commands/preprocess.py
etherdump/commands/pull.py
etherdump/commands/pushhtml.py
etherdump/commands/revisionscount.py
etherdump/commands/sethtml.py
etherdump/commands/settext.py
etherdump/commands/showmeta.py
etherdump/commands/status.py
etherdump/commands/template.py
etherdump/data/templates/index.html
etherdump/data/templates/pad.html
etherdump/data/templates/rss.xml
etherdump/data/templates/static/index.css
etherdump/data/templates/static/index.js
etherdump/data/templates/static/sortable.css
etherdump/data/templates/static/sortable.js
etherdump-1.0.3.dist-info/METADATA
etherdump-1.0.3.dist-info/WHEEL
etherdump-1.0.3.dist-info/entry_points.txt
etherdump-1.0.3.dist-info/licenses/LICENSE.txt
etherdump-1.0.3.dist-info/RECORD
