Metadata-Version: 2.4
Name: etherdump
Version: 1.0.3
Summary: a set of utilities for using the etherpad API to make static dumps of pads
Project-URL: Homepage, https://gitlab.constantvzw.org/aa/etherdump
Author-email: Michael Murtaugh <mm@automatist.org>
License-Expression: GPL-3.0-or-later
License-File: LICENSE.txt
Requires-Python: >=3.12
Requires-Dist: click>=8.1.8
Requires-Dist: html5lib>=1.1
Requires-Dist: jinja2>=3.1.6
Requires-Dist: python-dateutil>=2.9.0.post0
Requires-Dist: requests-oauthlib>=2.0.0
